.coveragerc
.pylintrc
LICENSE
MANIFEST.in
Makefile
README.rst
dumprar.py
rarfile.py
setup.cfg
setup.py
tox.ini
.github/workflows/ci.yml
.github/workflows/release.yml
doc/Makefile
doc/api.rst
doc/conf.py
doc/faq.rst
doc/index.rst
doc/make.bat
doc/news.rst
doc/note.awk
rarfile.egg-info/PKG-INFO
rarfile.egg-info/SOURCES.txt
rarfile.egg-info/dependency_links.txt
rarfile.egg-info/top_level.txt
test/__init__.py
test/run_dump.sh
test/run_dump_all.sh
test/test_api.py
test/test_crypto.py
test/test_format.py
test/test_hashing.py
test/test_korrupt.py
test/test_reading.py
test/test_seek.py
test/test_tool.py
test/files/ctime0.rar
test/files/ctime0.rar.exp
test/files/ctime1.rar
test/files/ctime1.rar.exp
test/files/ctime2.rar
test/files/ctime2.rar.exp
test/files/ctime3.rar
test/files/ctime3.rar.exp
test/files/ctime4.rar
test/files/ctime4.rar.exp
test/files/rar15-comment-lock.rar
test/files/rar15-comment-lock.rar.exp
test/files/rar15-comment.rar
test/files/rar15-comment.rar.exp
test/files/rar202-comment-nopsw.rar
test/files/rar202-comment-nopsw.rar.exp
test/files/rar202-comment-psw.rar
test/files/rar202-comment-psw.rar.exp
test/files/rar3-comment-hpsw.rar
test/files/rar3-comment-hpsw.rar.exp
test/files/rar3-comment-plain.rar
test/files/rar3-comment-plain.rar.exp
test/files/rar3-comment-psw.rar
test/files/rar3-comment-psw.rar.exp
test/files/rar3-old.r00
test/files/rar3-old.r01
test/files/rar3-old.rar
test/files/rar3-old.rar.exp
test/files/rar3-seektest.sfx
test/files/rar3-vols.part1.rar
test/files/rar3-vols.part1.rar.exp
test/files/rar3-vols.part2.rar
test/files/rar3-vols.part2.rar.exp
test/files/rar3-vols.part3.rar
test/files/rar3-vols.part3.rar.exp
test/files/rar5-blake.rar
test/files/rar5-blake.rar.exp
test/files/rar5-crc.rar
test/files/rar5-crc.rar.exp
test/files/rar5-crc.sfx
test/files/rar5-dups.rar
test/files/rar5-dups.rar.exp
test/files/rar5-hlink.rar
test/files/rar5-hlink.rar.exp
test/files/rar5-hpsw.rar
test/files/rar5-hpsw.rar.exp
test/files/rar5-psw-blake.rar
test/files/rar5-psw-blake.rar.exp
test/files/rar5-psw.rar
test/files/rar5-psw.rar.exp
test/files/rar5-quick-open.rar
