Metadata-Version: 1.1
Name: rarfile
Version: 3.3
Summary: RAR archive reader for Python
Home-page: https://github.com/markokr/rarfile
Author: Marko Kreen
Author-email: markokr@gmail.com
License: ISC
Keywords: rar,unrar,archive
Platform: UNKNOWN
Classifier: Development Status :: 5 - Production/Stable
Classifier: Intended Audience :: Developers
Classifier: License :: OSI Approved :: ISC License (ISCL)
Classifier: Operating System :: OS Independent
Classifier: Programming Language :: Python :: 3
Classifier: Topic :: Software Development :: Libraries :: Python Modules
Classifier: Topic :: System :: Archiving :: Compression
